trackus_revelio/__init__.py
trackus_revelio/trackus_revelio.py
trackus_revelio-0.1.5.dist-info/METADATA
trackus_revelio-0.1.5.dist-info/WHEEL
trackus_revelio-0.1.5.dist-info/RECORD
